{
  "hints": [],
  "groups": [
    {
      "sourceType": "slack_impl.Channels",
      "name": "",
      "type": "slack_impl.Channels"
    },
    {
      "sourceType": "slack_impl.SlackConfigs",
      "name": "",
      "type": "slack_impl.SlackConfigs"
    }
  ],
  "properties": [
    {
      "sourceType": "slack_impl.SlackConfigs",
      "name": "auth-token",
      "type": "java.lang.String"
    },
    {
      "sourceType": "slack_impl.Channels",
      "name": "channels",
      "type": "java.util.List<java.lang.String>"
    }
  ]
}